lickport_array_interface/__about__.py
lickport_array_interface/__init__.py
lickport_array_interface/lickport_array_interface.py
lickport_array_interface-2.0.1.dist-info/LICENSE
lickport_array_interface-2.0.1.dist-info/METADATA
lickport_array_interface-2.0.1.dist-info/WHEEL
lickport_array_interface-2.0.1.dist-info/top_level.txt
lickport_array_interface-2.0.1.dist-info/RECORD
