Metadata-Version: 2.1
Name: lickport-array-interface
Version: 2.0.1
Summary: Python interface to the Janelia Dudman lab mouse lickport array.
Home-page: https://github.com/janelia-pypi/lickport_array_interface_python
Author: Peter Polidoro
Author-email: peter@polidoro.io
License: BSD 3-Clause License
Platform: UNKNOWN
Classifier: Programming Language :: Python :: 3
License-File: LICENSE
Requires-Dist: modular-client
